deepneuro/__init__.py
deepneuro/core.py
deepneuro/augmentation/__init__.py
deepneuro/augmentation/augment.py
deepneuro/augmentation/subsample.py
deepneuro/container/__init__.py
deepneuro/container/container_cli.py
deepneuro/container/deploy.py
deepneuro/data/__init__.py
deepneuro/data/data_collection.py
deepneuro/data/data_group.py
deepneuro/data/data_load.py
deepneuro/data/data_split.py
deepneuro/data/data_utilities.py
deepneuro/data/sampling.py
deepneuro/external/__init__.py
deepneuro/interface/__init__.py
deepneuro/interface/master_cli.py
deepneuro/interface/web_wrapper.py
deepneuro/load/__init__.py
deepneuro/load/load.py
deepneuro/models/__init__.py
deepneuro/models/blocks.py
deepneuro/models/callbacks.py
deepneuro/models/cost_functions.py
deepneuro/models/dn_ops.py
deepneuro/models/gan.py
deepneuro/models/keras_model.py
deepneuro/models/keras_pretrained.py
deepneuro/models/minimal.py
deepneuro/models/model.py
deepneuro/models/ops.py
deepneuro/models/progressive_growing_gan.py
deepneuro/models/tensorflow_model.py
deepneuro/models/unet.py
deepneuro/outputs/__init__.py
deepneuro/outputs/classification.py
deepneuro/outputs/gan.py
deepneuro/outputs/inference.py
deepneuro/outputs/interpretability.py
deepneuro/outputs/measure.py
deepneuro/outputs/output.py
deepneuro/outputs/radiomics.py
deepneuro/outputs/segmentation.py
deepneuro/outputs/statistics.py
deepneuro/outputs/toy.py
deepneuro/outputs/visualization.py
deepneuro/package_test/__init__.py
deepneuro/package_test/ci_test.py
deepneuro/package_test/package_test.py
deepneuro/package_test/pipeline_test.py
deepneuro/package_test/utilities_test.py
deepneuro/pipelines/__init__.py
deepneuro/pipelines/shared.py
deepneuro/pipelines/template.py
deepneuro/pipelines/Ischemic_Stroke/__init__.py
deepneuro/pipelines/Ischemic_Stroke/cli.py
deepneuro/pipelines/Ischemic_Stroke/predict.py
deepneuro/pipelines/Ischemic_Stroke/train.py
deepneuro/pipelines/Segment_Brain_Mets/__init__.py
deepneuro/pipelines/Segment_Brain_Mets/cli.py
deepneuro-0.2.2.dist-info/LICENSE
deepneuro-0.2.2.dist-info/METADATA
deepneuro-0.2.2.dist-info/WHEEL
deepneuro-0.2.2.dist-info/entry_points.txt
deepneuro-0.2.2.dist-info/top_level.txt
deepneuro-0.2.2.dist-info/RECORD
