Metadata-Version: 2.1
Name: deepneuro
Version: 0.2.2
Summary: DeepNeuro: A deep learning python package for neuroimaging data.
Home-page: https://github.com/QTIM-Lab/DeepNeuro
Author: Andrew Beers
Author-email: abeers@mgh.harvard.edu
License: UNKNOWN
Download-URL: https://github.com/QTIM-Lab/DeepNeuro/tarball/0.2.2
Keywords: neuroimaging,neuroncology,neural networks,neuroscience,neurology,deep learning,fmri,pet,mri,dce,dsc,dti,machine learning,computer vision,learning,keras,theano,tensorflow,nifti,nrrd,dicom
Platform: UNKNOWN
Requires-Dist: tables
Requires-Dist: pydicom
Requires-Dist: pynrrd
Requires-Dist: nibabel
Requires-Dist: pyyaml
Requires-Dist: six
Requires-Dist: imageio
Requires-Dist: matplotlib
Requires-Dist: pydot
Requires-Dist: scipy
Requires-Dist: numpy
Requires-Dist: scikit-image
Requires-Dist: tqdm
